setup.py
torflaio_validators/__init__.py
torflaio_validators.egg-info/PKG-INFO
torflaio_validators.egg-info/SOURCES.txt
torflaio_validators.egg-info/dependency_links.txt
torflaio_validators.egg-info/requires.txt
torflaio_validators.egg-info/top_level.txt
torflaio_validators/base/__init__.py
torflaio_validators/base/base_validator.py
torflaio_validators/base/exceptions.py
torflaio_validators/base/fields.py
torflaio_validators/base/time_tools.py