Metadata-Version: 1.0
Name: torflaio-validators
Version: 1.0.1
Summary: Tornado, Flask, AioHttp params validators
Home-page: https://github.com/yirantai/torflaio_validators.git
Author: yirantai
Author-email: 896275756@qq.com
License: BSD License
Platform: UNKNOWN
